django_celery_task_api/__init__.py
django_celery_task_api/apps.py
django_celery_task_api/utils.py
django_celery_task_api/views.py
django_celery_task_api-0.2.dist-info/LICENSE
django_celery_task_api-0.2.dist-info/METADATA
django_celery_task_api-0.2.dist-info/WHEEL
django_celery_task_api-0.2.dist-info/top_level.txt
django_celery_task_api-0.2.dist-info/RECORD
