Metadata-Version: 2.1
Name: django-celery-task-api
Version: 0.2
Summary: Celery task API for Django
Home-page: https://github.com/loganbibby/django-celery-task-api
Author: Logan Bibby <me@loganbibby.com>
Classifier: Programming Language :: Python :: 3
Classifier: License :: OSI Approved :: BSD License
Classifier: Operating System :: OS Independent
Requires-Python: >=3.6
License-File: LICENSE
Requires-Dist: django (>=2.2.9)
Requires-Dist: celery (>=5.1.2)
